<?xml version="1.0" encoding="utf-8" ?>
<dwsync>
<file name="colourSelector.php" server="green.e64.com//alloygater.pre64.co.uk/wwwroot/" local="132126672698847382" remote="132126672600000000" />
<file name="selector-template.html" server="green.e64.com//alloygater.pre64.co.uk/wwwroot/" local="132126670341942905" remote="132126672000000000" />
<file name="colour-boxes.html" server="green.e64.com//alloygater.pre64.co.uk/wwwroot/" local="132089747061407160" remote="132089746800000000" />
<file name="alloy-colours.html" server="green.e64.com//alloygater.pre64.co.uk/wwwroot/" local="132085326468978586" remote="132085327800000000" />
<file name="colourSelector.php" server="109.169.42.104//alloygater.pre64.co.uk/wwwroot/" local="132143561173303127" remote="132143560800000000" />
<file name="selector-template.html" server="109.169.42.104//alloygater.pre64.co.uk/wwwroot/" local="132143531888575640" remote="132143531400000000" />
<file name="alloy-colours.html" server="109.169.42.104//alloygater.pre64.co.uk/wwwroot/" local="132085326468978586" remote="132134511000000000" />
<file name="colour-boxes.html" server="109.169.42.104//alloygater.pre64.co.uk/wwwroot/" local="132143529603485940" remote="132143529600000000" />
</dwsync>