<?xml version="1.0" encoding="utf-8" ?>
<dwsync>
<file name="Audi.png" server="green.e64.com//alloygater.pre64.co.uk/wwwroot/" local="132086182210000000" remote="132086189400000000" />
<file name="Bentley.png" server="green.e64.com//alloygater.pre64.co.uk/wwwroot/" local="132086182100000000" remote="132086189400000000" />
<file name="BMW.png" server="green.e64.com//alloygater.pre64.co.uk/wwwroot/" local="132086182880000000" remote="132086189400000000" />
<file name="Caravans.png" server="green.e64.com//alloygater.pre64.co.uk/wwwroot/" local="132086195416080058" remote="132086194800000000" />
<file name="Chevrolet.png" server="green.e64.com//alloygater.pre64.co.uk/wwwroot/" local="132086182840000000" remote="132086189400000000" />
<file name="Ferrari.png" server="green.e64.com//alloygater.pre64.co.uk/wwwroot/" local="132086183160000000" remote="132086189400000000" />
<file name="Fiat.png" server="green.e64.com//alloygater.pre64.co.uk/wwwroot/" local="132086182800000000" remote="132086189400000000" />
<file name="Land Rover.png" server="green.e64.com//alloygater.pre64.co.uk/wwwroot/" local="132086182650000000" remote="132086189400000000" />
<file name="Maserati.png" server="green.e64.com//alloygater.pre64.co.uk/wwwroot/" local="132086182270000000" remote="132086189400000000" />
<file name="Mercedes Benz.png" server="green.e64.com//alloygater.pre64.co.uk/wwwroot/" local="132086182770000000" remote="132086189400000000" />
<file name="Porsche.png" server="green.e64.com//alloygater.pre64.co.uk/wwwroot/" local="132086182820000000" remote="132086189400000000" />
<file name="Tesla.png" server="green.e64.com//alloygater.pre64.co.uk/wwwroot/" local="132086182160000000" remote="132086189400000000" />
<file name="Volkswagen.png" server="green.e64.com//alloygater.pre64.co.uk/wwwroot/" local="132086182720000000" remote="132086189400000000" />
<file name="Alfa Romeo.png" server="green.e64.com//alloygater.pre64.co.uk/wwwroot/" local="132086182310000000" remote="132086191200000000" />
<file name="all.png" server="green.e64.com//alloygater.pre64.co.uk/wwwroot/" local="132089780897499840" remote="132089781000000000" />
<file name="Alfa Romeo.png" server="109.169.42.104//alloygater.pre64.co.uk/wwwroot/" local="132086182310000000" remote="132134511600000000" />
<file name="all.png" server="109.169.42.104//alloygater.pre64.co.uk/wwwroot/" local="132089780897499840" remote="132134511600000000" />
<file name="Audi.png" server="109.169.42.104//alloygater.pre64.co.uk/wwwroot/" local="132086182210000000" remote="132134511600000000" />
<file name="Bentley.png" server="109.169.42.104//alloygater.pre64.co.uk/wwwroot/" local="132086182100000000" remote="132134511600000000" />
<file name="BMW.png" server="109.169.42.104//alloygater.pre64.co.uk/wwwroot/" local="132086182880000000" remote="132134511600000000" />
<file name="Caravans.png" server="109.169.42.104//alloygater.pre64.co.uk/wwwroot/" local="132086195416080058" remote="132134511600000000" />
<file name="Chevrolet.png" server="109.169.42.104//alloygater.pre64.co.uk/wwwroot/" local="132086182840000000" remote="132134511600000000" />
<file name="Ferrari.png" server="109.169.42.104//alloygater.pre64.co.uk/wwwroot/" local="132086183160000000" remote="132134511600000000" />
<file name="Fiat.png" server="109.169.42.104//alloygater.pre64.co.uk/wwwroot/" local="132086182800000000" remote="132134511600000000" />
<file name="Land Rover.png" server="109.169.42.104//alloygater.pre64.co.uk/wwwroot/" local="132086182650000000" remote="132134511600000000" />
<file name="Maserati.png" server="109.169.42.104//alloygater.pre64.co.uk/wwwroot/" local="132086182270000000" remote="132134511600000000" />
<file name="Mercedes Benz.png" server="109.169.42.104//alloygater.pre64.co.uk/wwwroot/" local="132086182770000000" remote="132134511600000000" />
<file name="Porsche.png" server="109.169.42.104//alloygater.pre64.co.uk/wwwroot/" local="132086182820000000" remote="132134511600000000" />
<file name="Tesla.png" server="109.169.42.104//alloygater.pre64.co.uk/wwwroot/" local="132086182160000000" remote="132134511600000000" />
<file name="Volkswagen.png" server="109.169.42.104//alloygater.pre64.co.uk/wwwroot/" local="132086182720000000" remote="132134511600000000" />
</dwsync>